mchange/__init__.py
mchange-1.0.dist-info/METADATA
mchange-1.0.dist-info/WHEEL
mchange-1.0.dist-info/top_level.txt
mchange-1.0.dist-info/RECORD
