Metadata-Version: 2.1
Name: mchange
Version: 1.0
Summary: Fast and Free currency converter that uses Xe.
Home-page: https://github.com/mc-c0rp/mchange
Author: mc_c0rp
Author-email: mc.c0rp@icloud.com
Classifier: Programming Language :: Python :: 3
Classifier: License :: OSI Approved :: MIT License
Classifier: Operating System :: OS Independent
Requires-Python: >=3.6
Requires-Dist: bs4
Requires-Dist: requests
